mintflow/__init__.py
mintflow/anneal_decoder_xintxspl.py
mintflow/generativemodel.py
mintflow/kl_annealing.py
mintflow/masking.py
mintflow/predadjmat.py
mintflow/probutils.py
mintflow/utils.py
mintflow/utils_flowmatching.py
mintflow/utils_imputer.py
mintflow/utils_multislice.py
mintflow/utils_pyg.py
mintflow/vardist.py
mintflow/wassdist_utils.py
mintflow/wassdist_utils_batchID.py
mintflow/zs_samplers.py
mintflow/data/__init__.py
mintflow/data/default_config_files/__init__.py
mintflow/data/default_config_files/config_data_evaluation.yml
mintflow/data/default_config_files/config_data_train.yml
mintflow/data/default_config_files/config_model.yml
mintflow/data/default_config_files/config_training.yml
mintflow/data/for_evaluation/__init__.py
mintflow/data/for_evaluation/db_signalling_genes/__init__.py
mintflow/data/for_evaluation/db_signalling_genes/df_LRpairs_Armingoletal.txt
mintflow/data/for_evaluation/mcc_predictability_precomputed_gene_scores/__init__.py
mintflow/data/for_evaluation/mcc_predictability_precomputed_gene_scores/skin/melanoma_public_sample.pkl
mintflow/evaluation/__init__.py
mintflow/evaluation/base_evaluation.py
mintflow/evaluation/bioconsv.py
mintflow/evaluation/db_signalling_genes.py
mintflow/evaluation/db_spatial_gene_scores.py
mintflow/evaluation/mcp_predictability.py
mintflow/evaluation/predxspl.py
mintflow/evaluation/sciblike_clustering.py
mintflow/interface/__init__.py
mintflow/interface/auxiliary_modules.py
mintflow/interface/base_interface.py
mintflow/interface/check_listtissue_trtest.py
mintflow/interface/module_parse_config_data_evaluation.py
mintflow/interface/module_parse_config_data_train.py
mintflow/interface/module_parse_config_model.py
mintflow/interface/module_parse_config_training.py
mintflow/interface/module_predict.py
mintflow/interface/module_setup_data.py
mintflow/interface/module_setup_model.py
mintflow/interface/setup_trainer.py
mintflow/interface/analresults/__init__.py
mintflow-0.2.0.dist-info/METADATA
mintflow-0.2.0.dist-info/WHEEL
mintflow-0.2.0.dist-info/licenses/LICENSE
mintflow-0.2.0.dist-info/RECORD
