Metadata-Version: 2.4
Name: mintflow
Version: 0.2.0
Summary: Microenvironment-induced and INtrinsic Transcriptomic FLOWs
Project-URL: Documentation, https://mintflow.readthedocs.io/
Project-URL: Source, https://github.com/Lotfollahi-lab/mintflow
Project-URL: Home-page, https://github.com/Lotfollahi-lab/mintflow
Author: Amir Hossein Hosseini Akbarnejad, Sebastian Birk
Maintainer-email: Amir Hossein Hosseini Akbarnejad <aa36@sanger.ac.uk>, Sebastian Birk <sebastian.birk@outlook.com>
License: BSD 3-Clause License
License-File: LICENSE
Classifier: Development Status :: 3 - Alpha
Classifier: Intended Audience :: Science/Research
Classifier: Natural Language :: English
Classifier: Operating System :: POSIX :: Linux
Classifier: Programming Language :: Python :: 3.10
Classifier: Programming Language :: Python :: 3.11
Classifier: Topic :: Scientific/Engineering :: Bio-Informatics
Requires-Python: <3.13,>=3.10
Requires-Dist: anndata
Requires-Dist: gdown
Requires-Dist: ipython
Requires-Dist: linformer-pytorch
Requires-Dist: pillow
Requires-Dist: pyyaml
Requires-Dist: scib-metrics
Requires-Dist: scikit-learn
Requires-Dist: scipy
Requires-Dist: scvi-tools
Requires-Dist: spatialdata>=0.2.5
Requires-Dist: squidpy
Requires-Dist: torch
Requires-Dist: torch-geometric
Requires-Dist: torchcfm
Requires-Dist: torchdyn
Requires-Dist: wandb
Requires-Dist: zarr<3.0.0,>=2.6.1
Provides-Extra: all
Requires-Dist: coverage; extra == 'all'
Requires-Dist: docutils!=0.18.*,!=0.19.*,>=0.8; extra == 'all'
Requires-Dist: ipykernel; extra == 'all'
Requires-Dist: ipython; extra == 'all'
Requires-Dist: jupyterlab; extra == 'all'
Requires-Dist: myst-nb; extra == 'all'
Requires-Dist: myst-parser; extra == 'all'
Requires-Dist: pandas; extra == 'all'
Requires-Dist: pre-commit; extra == 'all'
Requires-Dist: pytest; extra == 'all'
Requires-Dist: sphinx-autodoc-typehints; extra == 'all'
Requires-Dist: sphinx-book-theme>=1.0.0; extra == 'all'
Requires-Dist: sphinx-copybutton; extra == 'all'
Requires-Dist: sphinx-design; extra == 'all'
Requires-Dist: sphinx-hoverxref; extra == 'all'
Requires-Dist: sphinx-rtd-theme; extra == 'all'
Requires-Dist: sphinx>=4.1; extra == 'all'
Requires-Dist: sphinxcontrib-bibtex>=1.0.0; extra == 'all'
Requires-Dist: sphinxext-opengraph; extra == 'all'
Requires-Dist: twine>=4.0.2; extra == 'all'
Provides-Extra: dev
Requires-Dist: pre-commit; extra == 'dev'
Requires-Dist: twine>=4.0.2; extra == 'dev'
Provides-Extra: docs
Requires-Dist: docutils!=0.18.*,!=0.19.*,>=0.8; extra == 'docs'
Requires-Dist: ipykernel; extra == 'docs'
Requires-Dist: ipython; extra == 'docs'
Requires-Dist: myst-nb; extra == 'docs'
Requires-Dist: myst-parser; extra == 'docs'
Requires-Dist: pandas; extra == 'docs'
Requires-Dist: sphinx-autodoc-typehints; extra == 'docs'
Requires-Dist: sphinx-book-theme>=1.0.0; extra == 'docs'
Requires-Dist: sphinx-copybutton; extra == 'docs'
Requires-Dist: sphinx-design; extra == 'docs'
Requires-Dist: sphinx-hoverxref; extra == 'docs'
Requires-Dist: sphinx-rtd-theme; extra == 'docs'
Requires-Dist: sphinx>=4.1; extra == 'docs'
Requires-Dist: sphinxcontrib-bibtex>=1.0.0; extra == 'docs'
Requires-Dist: sphinxext-opengraph; extra == 'docs'
Provides-Extra: docsbuild
Requires-Dist: docutils!=0.18.*,!=0.19.*,>=0.8; extra == 'docsbuild'
Requires-Dist: ipykernel; extra == 'docsbuild'
Requires-Dist: ipython; extra == 'docsbuild'
Requires-Dist: myst-nb; extra == 'docsbuild'
Requires-Dist: myst-parser; extra == 'docsbuild'
Requires-Dist: pandas; extra == 'docsbuild'
Requires-Dist: sphinx-autodoc-typehints; extra == 'docsbuild'
Requires-Dist: sphinx-book-theme>=1.0.0; extra == 'docsbuild'
Requires-Dist: sphinx-copybutton; extra == 'docsbuild'
Requires-Dist: sphinx-design; extra == 'docsbuild'
Requires-Dist: sphinx-hoverxref; extra == 'docsbuild'
Requires-Dist: sphinx-rtd-theme; extra == 'docsbuild'
Requires-Dist: sphinx>=4.1; extra == 'docsbuild'
Requires-Dist: sphinxcontrib-bibtex>=1.0.0; extra == 'docsbuild'
Requires-Dist: sphinxext-opengraph; extra == 'docsbuild'
Provides-Extra: tests
Requires-Dist: coverage; extra == 'tests'
Requires-Dist: pytest; extra == 'tests'
Provides-Extra: tutorials
Requires-Dist: jupyterlab; extra == 'tutorials'
